fmtpy/__init__.py
fmtpy/cli.py
fmtpy/fmtpy.py
fmtpy-0.1.dist-info/entry_points.txt
fmtpy-0.1.dist-info/LICENSE
fmtpy-0.1.dist-info/WHEEL
fmtpy-0.1.dist-info/METADATA
fmtpy-0.1.dist-info/RECORD
