Metadata-Version: 2.1
Name: fmtpy
Version: 0.1
Summary: Formats python files with properly sorted import statemnts
Author-email: Alyetama <56323389+Alyetama@users.noreply.github.com>
Classifier: License :: OSI Approved :: MIT License
Requires-Dist: requests~=2.27.1
Requires-Dist: beautifulsoup4~=4.10.0
Requires-Dist: rich~=10.11.0
Requires-Dist: yapf~=0.32.0
Project-URL: Home, https://github.comm/Alyetama/fmtpy
